{
  "id": "pf2e-counteract-helper",
  "type": "module",
  "title": "PF2e Counteract Helper",
  "description": "Rolls and explains PF2e counteract checks with a clear chat summary.",
  "version": "0.1.2",
  "authors": [
    {
      "name": "Home Brew Crew"
    }
  ],
  "compatibility": {
    "minimum": "12",
    "verified": "13"
  },
  
  "esmodules": [
    "scripts/main.js"
  ],
  "readme": "README.md",
  "bugs": "",
  "url": "https://github.com/kobseryqum/pf2e-counteract-helper",
  "manifest": "https://github.com/kobseryqum/pf2e-counteract-helper/releases/download/latest/module.json",
  "download": "https://github.com/kobseryqum/pf2e-counteract-helper/",
  
}
